LICENSE
MANIFEST.in
README.rst
pyproject.toml
setup.cfg
setup.py
django_webdav_ui.egg-info/PKG-INFO
django_webdav_ui.egg-info/SOURCES.txt
django_webdav_ui.egg-info/dependency_links.txt
django_webdav_ui.egg-info/requires.txt
django_webdav_ui.egg-info/top_level.txt
webdav/__init__.py
webdav/admin.py
webdav/apis.py
webdav/apps.py
webdav/client.py
webdav/filters.py
webdav/forms.py
webdav/models.py
webdav/receivers.py
webdav/serializers.py
webdav/signals.py
webdav/tests.py
webdav/urls.py
webdav/utils.py
webdav/views.py
webdav/components/README.md
webdav/components/webdav.jsx
webdav/components/components/ActivityBox.jsx
webdav/components/components/ActivityLine.jsx
webdav/components/components/BatchButton.jsx
webdav/components/components/CommentBox.jsx
webdav/components/components/CommentLine.jsx
webdav/components/components/CreateFolderButton.jsx
webdav/components/components/CreateFolderDialog.jsx
webdav/components/components/DavBody.jsx
webdav/components/components/DirectoryBreadcrumbs.jsx
webdav/components/components/DownloadMenu.jsx
webdav/components/components/FileActions.jsx
webdav/components/components/FileDeleteDialog.jsx
webdav/components/components/FileDeleteMenu.jsx
webdav/components/components/FileName.jsx
webdav/components/components/FilePreview.jsx
webdav/components/components/FileSummary.jsx
webdav/components/components/FilesTable.jsx
webdav/components/components/LeftPanel.jsx
webdav/components/components/Preview.jsx
webdav/components/components/RenameDialog.jsx
webdav/components/components/RenameMenu.jsx
webdav/components/components/ShareBox.jsx
webdav/components/components/Sidebar.jsx
webdav/components/components/Topbar.jsx
webdav/components/components/UploadButton.jsx
webdav/components/context/batch.jsx
webdav/components/context/directory-context.jsx
webdav/components/utils/utils.jsx
webdav/migrations/0001_initial.py
webdav/migrations/__init__.py
webdav/static/webdav/bulma.min.css
webdav/static/webdav/dist/manifest.json
webdav/static/webdav/dist/assets/webdav-07e1678a.js
webdav/templates/webdav/base.html
webdav/templates/webdav/index.html
webdav/templates/webdav/share.html
webdav/templates/webdav/share_auth.html